<?xml version="1.0" encoding="utf-8" ?>
<dwsync>
<file name="oceanie.php" server="berlioz.cc.uottawa.ca//var/www/html/http/weblaw/world-legal-systems/" local="129053762088312605" remote="129053830610000000" />
<file name="asie.php" server="berlioz.cc.uottawa.ca//var/www/html/http/weblaw/world-legal-systems/" local="129053762087062597" remote="129053830610000000" />
<file name="caucase.php" server="berlioz.cc.uottawa.ca//var/www/html/http/weblaw/world-legal-systems/" local="129053762087375099" remote="129053830610000000" />
<file name="moy-orient.php" server="berlioz.cc.uottawa.ca//var/www/html/http/weblaw/world-legal-systems/" local="129053762088000103" remote="129053830610000000" />
<file name="amer-sud.php" server="berlioz.cc.uottawa.ca//var/www/html/http/weblaw/world-legal-systems/" local="129053762086281342" remote="129053830610000000" />
<file name="amer-nord.php" server="berlioz.cc.uottawa.ca//var/www/html/http/weblaw/world-legal-systems/" local="129053762086125091" remote="129053830610000000" />
<file name="antilles.php" server="berlioz.cc.uottawa.ca//var/www/html/http/weblaw/world-legal-systems/" local="129053762086593844" remote="129053830610000000" />
<file name="monde.php" server="berlioz.cc.uottawa.ca//var/www/html/http/weblaw/world-legal-systems/" local="128786819680000000" remote="129053830610000000" />
<file name="asie-sud-est.php" server="berlioz.cc.uottawa.ca//var/www/html/http/weblaw/world-legal-systems/" local="129053762086906346" remote="129053830610000000" />
<file name="amer-cent.php" server="berlioz.cc.uottawa.ca//var/www/html/http/weblaw/world-legal-systems/" local="129053762085968840" remote="129053830610000000" />
<file name="europe.php" server="berlioz.cc.uottawa.ca//var/www/html/http/weblaw/world-legal-systems/" local="129053762087687601" remote="129053830610000000" />
<file name="afrique.php" server="berlioz.cc.uottawa.ca//var/www/html/http/weblaw/world-legal-systems/" local="129053762085187585" remote="129053830610000000" />
</dwsync>